seisclass/__init__.py
seisclass/check_wave.py
seisclass/samples.py
seisclass/model/251111nw/event_model.h5
seisclass/model/251111nw/event_model.json
seisclass/model/251111nw/event_model.pkl
seisclass/packages/read_phase.py
seisclass-0.1.8.dist-info/LICENSE
seisclass-0.1.8.dist-info/METADATA
seisclass-0.1.8.dist-info/WHEEL
seisclass-0.1.8.dist-info/top_level.txt
seisclass-0.1.8.dist-info/RECORD
