Metadata-Version: 2.1
Name: seisclass
Version: 0.1.8
Summary: Seismic event classification package
Home-page: https://github.com/epnet2018/seisclass
Author: Jia Luozhao
Author-email: Jia Luozhao <lezhao.jia@gmail.com>
License: MIT License
Project-URL: homepage, https://github.com/epnet2018/seisclass
Classifier: Programming Language :: Python :: 3
Classifier: License :: OSI Approved :: MIT License
Classifier: Operating System :: OS Independent
Requires-Python: >=3.6
License-File: LICENSE
Requires-Dist: numpy >=1.19.0
Requires-Dist: obspy >=1.2.0
Requires-Dist: tensorflow >=2.0.0
Requires-Dist: keras >=2.3.0
Requires-Dist: joblib >=1.0.0
Requires-Dist: scikit-learn >=0.24.0
Requires-Dist: pandas >=1.1.0
Provides-Extra: test
Requires-Dist: pytest ; extra == 'test'
